[ {
  "date" : "20140609",
  "summary" : [ {
    "activity" : "walking",
    "group" : "walking",
    "duration" : 3060.0,
    "distance" : 3481.0,
    "steps" : 5136,
    "calories" : 227
  } ],
  "segments" : [ {
    "type" : "place",
    "startTime" : "20140608T191003-0400",
    "endTime" : "20140609T220553-0400",
    "place" : {
      "id" : 9869005,
      "name" : "Home",
      "type" : "home",
      "location" : {
        "lat" : 42.3754311174,
        "lon" : -71.1114458017
      }
    },
    "activities" : [ {
      "activity" : "walking",
      "group" : "walking",
      "manual" : false,
      "startTime" : "20140609T085044-0400",
      "endTime" : "20140609T085144-0400",
      "duration" : 60.0,
      "distance" : 51.0,
      "steps" : 101,
      "calories" : 3,
      "trackPoints" : [ ]
    }, {
      "activity" : "walking",
      "group" : "walking",
      "manual" : false,
      "startTime" : "20140609T091045-0400",
      "endTime" : "20140609T091115-0400",
      "duration" : 30.0,
      "distance" : 30.0,
      "steps" : 61,
      "calories" : 2,
      "trackPoints" : [ ]
    }, {
      "activity" : "walking",
      "group" : "walking",
      "manual" : false,
      "startTime" : "20140609T100042-0400",
      "endTime" : "20140609T100242-0400",
      "duration" : 120.0,
      "distance" : 86.0,
      "steps" : 172,
      "calories" : 6,
      "trackPoints" : [ ]
    }, {
      "activity" : "walking",
      "group" : "walking",
      "manual" : false,
      "startTime" : "20140609T115205-0400",
      "endTime" : "20140609T115235-0400",
      "duration" : 30.0,
      "distance" : 20.0,
      "steps" : 41,
      "calories" : 1,
      "trackPoints" : [ ]
    }, {
      "activity" : "walking",
      "group" : "walking",
      "manual" : false,
      "startTime" : "20140609T123929-0400",
      "endTime" : "20140609T123959-0400",
      "duration" : 30.0,
      "distance" : 25.0,
      "steps" : 51,
      "calories" : 2,
      "trackPoints" : [ ]
    }, {
      "activity" : "walking",
      "group" : "walking",
      "manual" : false,
      "startTime" : "20140609T130003-0400",
      "endTime" : "20140609T130203-0400",
      "duration" : 120.0,
      "distance" : 86.0,
      "steps" : 172,
      "calories" : 6,
      "trackPoints" : [ ]
    }, {
      "activity" : "walking",
      "group" : "walking",
      "manual" : false,
      "startTime" : "20140609T140032-0400",
      "endTime" : "20140609T140432-0400",
      "duration" : 240.0,
      "distance" : 304.0,
      "steps" : 406,
      "calories" : 20,
      "trackPoints" : [ ]
    }, {
      "activity" : "walking",
      "group" : "walking",
      "manual" : false,
      "startTime" : "20140609T164014-0400",
      "endTime" : "20140609T164344-0400",
      "duration" : 210.0,
      "distance" : 198.0,
      "steps" : 263,
      "calories" : 13,
      "trackPoints" : [ ]
    }, {
      "activity" : "walking",
      "group" : "walking",
      "manual" : false,
      "startTime" : "20140609T200633-0400",
      "endTime" : "20140609T200903-0400",
      "duration" : 150.0,
      "distance" : 167.0,
      "steps" : 223,
      "calories" : 11,
      "trackPoints" : [ ]
    }, {
      "activity" : "walking",
      "group" : "walking",
      "manual" : false,
      "startTime" : "20140609T213753-0400",
      "endTime" : "20140609T213923-0400",
      "duration" : 90.0,
      "distance" : 66.0,
      "steps" : 132,
      "calories" : 4,
      "trackPoints" : [ ]
    }, {
      "activity" : "walking",
      "group" : "walking",
      "manual" : false,
      "startTime" : "20140609T220206-0400",
      "endTime" : "20140609T220436-0400",
      "duration" : 150.0,
      "distance" : 113.0,
      "steps" : 132,
      "calories" : 7,
      "trackPoints" : [ ]
    } ],
    "lastUpdate" : "20140807T114103Z"
  }, {
    "type" : "move",
    "startTime" : "20140609T220553-0400",
    "endTime" : "20140609T221712-0400",
    "activities" : [ {
      "activity" : "walking",
      "group" : "walking",
      "manual" : false,
      "startTime" : "20140609T220553-0400",
      "endTime" : "20140609T221712-0400",
      "duration" : 679.0,
      "distance" : 969.0,
      "steps" : 1344,
      "calories" : 63,
      "trackPoints" : [ {
        "lat" : 42.3754311174,
        "lon" : -71.1114458017,
        "time" : "20140609T220553-0400"
      }, {
        "lat" : 42.3750918867,
        "lon" : -71.11156498,
        "time" : "20140609T220620-0400"
      }, {
        "lat" : 42.3751514532,
        "lon" : -71.1118748441,
        "time" : "20140609T220644-0400"
      }, {
        "lat" : 42.3752491015,
        "lon" : -71.1124638811,
        "time" : "20140609T220715-0400"
      }, {
        "lat" : 42.3752800279,
        "lon" : -71.1128408778,
        "time" : "20140609T220737-0400"
      }, {
        "lat" : 42.375222527,
        "lon" : -71.113228775,
        "time" : "20140609T220803-0400"
      }, {
        "lat" : 42.3753130435,
        "lon" : -71.1135689723,
        "time" : "20140609T220829-0400"
      }, {
        "lat" : 42.3754670061,
        "lon" : -71.1139511034,
        "time" : "20140609T220852-0400"
      }, {
        "lat" : 42.3755588427,
        "lon" : -71.1142937893,
        "time" : "20140609T220917-0400"
      }, {
        "lat" : 42.3755862519,
        "lon" : -71.1145512948,
        "time" : "20140609T220933-0400"
      }, {
        "lat" : 42.3755934164,
        "lon" : -71.1148518938,
        "time" : "20140609T220951-0400"
      }, {
        "lat" : 42.3756940736,
        "lon" : -71.1152148446,
        "time" : "20140609T221009-0400"
      }, {
        "lat" : 42.375658157,
        "lon" : -71.1155686982,
        "time" : "20140609T221033-0400"
      }, {
        "lat" : 42.3756877516,
        "lon" : -71.1160249644,
        "time" : "20140609T221057-0400"
      }, {
        "lat" : 42.3756390309,
        "lon" : -71.1163096494,
        "time" : "20140609T221120-0400"
      }, {
        "lat" : 42.3754854722,
        "lon" : -71.1166103002,
        "time" : "20140609T221143-0400"
      }, {
        "lat" : 42.3752550562,
        "lon" : -71.1169087828,
        "time" : "20140609T221207-0400"
      }, {
        "lat" : 42.3750511584,
        "lon" : -71.1171754871,
        "time" : "20140609T221228-0400"
      }, {
        "lat" : 42.374919036,
        "lon" : -71.1173560498,
        "time" : "20140609T221247-0400"
      }, {
        "lat" : 42.374800079,
        "lon" : -71.1176109561,
        "time" : "20140609T221310-0400"
      }, {
        "lat" : 42.3746706476,
        "lon" : -71.118347831,
        "time" : "20140609T221339-0400"
      }, {
        "lat" : 42.374582245,
        "lon" : -71.1185664258,
        "time" : "20140609T221403-0400"
      }, {
        "lat" : 42.374458311,
        "lon" : -71.1186691816,
        "time" : "20140609T221419-0400"
      }, {
        "lat" : 42.3741194387,
        "lon" : -71.118872137,
        "time" : "20140609T221445-0400"
      }, {
        "lat" : 42.3739536624,
        "lon" : -71.1188960113,
        "time" : "20140609T221501-0400"
      }, {
        "lat" : 42.3736973799,
        "lon" : -71.1188385593,
        "time" : "20140609T221524-0400"
      }, {
        "lat" : 42.3734506244,
        "lon" : -71.1186963419,
        "time" : "20140609T221549-0400"
      }, {
        "lat" : 42.3733328992,
        "lon" : -71.1185228738,
        "time" : "20140609T221613-0400"
      }, {
        "lat" : 42.3732446819,
        "lon" : -71.1183098241,
        "time" : "20140609T221636-0400"
      }, {
        "lat" : 42.3740293544,
        "lon" : -71.118991971,
        "time" : "20140609T221712-0400"
      } ]
    } ],
    "lastUpdate" : "20140610T025008Z"
  }, {
    "type" : "place",
    "startTime" : "20140609T221712-0400",
    "endTime" : "20140609T223832-0400",
    "place" : {
      "id" : 18127865,
      "name" : "CVS/pharmacy",
      "type" : "foursquare",
      "foursquareId" : "49df6a3ff964a520c6601fe3",
      "foursquareCategoryIds" : [ "4bf58dd8d48988d10f951735" ],
      "location" : {
        "lat" : 42.37402935435937,
        "lon" : -71.11899197101593
      }
    },
    "activities" : [ {
      "activity" : "walking",
      "group" : "walking",
      "manual" : false,
      "startTime" : "20140609T222207-0400",
      "endTime" : "20140609T222807-0400",
      "duration" : 360.0,
      "distance" : 502.0,
      "steps" : 669,
      "calories" : 33,
      "trackPoints" : [ ]
    } ],
    "lastUpdate" : "20140610T121801Z"
  }, {
    "type" : "move",
    "startTime" : "20140609T223832-0400",
    "endTime" : "20140609T225014-0400",
    "activities" : [ {
      "activity" : "walking",
      "group" : "walking",
      "manual" : false,
      "startTime" : "20140609T223832-0400",
      "endTime" : "20140609T225013-0400",
      "duration" : 701.0,
      "distance" : 819.0,
      "steps" : 1288,
      "calories" : 53,
      "trackPoints" : [ {
        "lat" : 42.373776,
        "lon" : -71.119043,
        "time" : "20140609T223832-0400"
      }, {
        "lat" : 42.3740421297,
        "lon" : -71.1191481694,
        "time" : "20140609T223851-0400"
      }, {
        "lat" : 42.374035568,
        "lon" : -71.1191374269,
        "time" : "20140609T223914-0400"
      }, {
        "lat" : 42.3741796206,
        "lon" : -71.1190204832,
        "time" : "20140609T223930-0400"
      }, {
        "lat" : 42.3744483323,
        "lon" : -71.1190189189,
        "time" : "20140609T223951-0400"
      }, {
        "lat" : 42.374343942,
        "lon" : -71.1189633212,
        "time" : "20140609T224017-0400"
      }, {
        "lat" : 42.3743071335,
        "lon" : -71.1188930848,
        "time" : "20140609T224038-0400"
      }, {
        "lat" : 42.3742784162,
        "lon" : -71.1187291999,
        "time" : "20140609T224059-0400"
      }, {
        "lat" : 42.3745392088,
        "lon" : -71.1181236354,
        "time" : "20140609T224132-0400"
      }, {
        "lat" : 42.3746155205,
        "lon" : -71.1178172651,
        "time" : "20140609T224152-0400"
      }, {
        "lat" : 42.3747905732,
        "lon" : -71.1174238452,
        "time" : "20140609T224228-0400"
      }, {
        "lat" : 42.3749120244,
        "lon" : -71.117315982,
        "time" : "20140609T224248-0400"
      }, {
        "lat" : 42.3751830547,
        "lon" : -71.1171895431,
        "time" : "20140609T224312-0400"
      }, {
        "lat" : 42.3754392787,
        "lon" : -71.1168228998,
        "time" : "20140609T224329-0400"
      }, {
        "lat" : 42.3756138737,
        "lon" : -71.1167375253,
        "time" : "20140609T224346-0400"
      }, {
        "lat" : 42.3756778526,
        "lon" : -71.1164743723,
        "time" : "20140609T224407-0400"
      }, {
        "lat" : 42.3756926615,
        "lon" : -71.1163171302,
        "time" : "20140609T224426-0400"
      }, {
        "lat" : 42.3757056451,
        "lon" : -71.1161051755,
        "time" : "20140609T224449-0400"
      }, {
        "lat" : 42.3756905116,
        "lon" : -71.1159166389,
        "time" : "20140609T224509-0400"
      }, {
        "lat" : 42.3756018022,
        "lon" : -71.1156895382,
        "time" : "20140609T224533-0400"
      }, {
        "lat" : 42.3755699866,
        "lon" : -71.1154373001,
        "time" : "20140609T224556-0400"
      }, {
        "lat" : 42.375554489,
        "lon" : -71.1152284556,
        "time" : "20140609T224611-0400"
      }, {
        "lat" : 42.3755581453,
        "lon" : -71.1149547178,
        "time" : "20140609T224634-0400"
      }, {
        "lat" : 42.3755614878,
        "lon" : -71.1144730674,
        "time" : "20140609T224657-0400"
      }, {
        "lat" : 42.3755898724,
        "lon" : -71.1137299734,
        "time" : "20140609T224719-0400"
      }, {
        "lat" : 42.3756116913,
        "lon" : -71.1136767934,
        "time" : "20140609T224735-0400"
      }, {
        "lat" : 42.3754628854,
        "lon" : -71.1134358884,
        "time" : "20140609T224752-0400"
      }, {
        "lat" : 42.3753796539,
        "lon" : -71.1130988054,
        "time" : "20140609T224819-0400"
      }, {
        "lat" : 42.375360927,
        "lon" : -71.1128923868,
        "time" : "20140609T224836-0400"
      }, {
        "lat" : 42.3753343459,
        "lon" : -71.1126389039,
        "time" : "20140609T224858-0400"
      }, {
        "lat" : 42.3752862925,
        "lon" : -71.1123878673,
        "time" : "20140609T224914-0400"
      }, {
        "lat" : 42.3752458732,
        "lon" : -71.1120842766,
        "time" : "20140609T224931-0400"
      }, {
        "lat" : 42.3752401377,
        "lon" : -71.1116524883,
        "time" : "20140609T224954-0400"
      }, {
        "lat" : 42.3754311174,
        "lon" : -71.1114458017,
        "time" : "20140609T225014-0400"
      } ]
    } ],
    "lastUpdate" : "20140610T054821Z"
  }, {
    "type" : "place",
    "startTime" : "20140609T225014-0400",
    "endTime" : "20140610T090439-0400",
    "place" : {
      "id" : 9869005,
      "name" : "Home",
      "type" : "home",
      "location" : {
        "lat" : 42.3754311174,
        "lon" : -71.1114458017
      }
    },
    "activities" : [ {
      "activity" : "walking",
      "group" : "walking",
      "manual" : false,
      "startTime" : "20140609T225136-0400",
      "endTime" : "20140609T225206-0400",
      "duration" : 30.0,
      "distance" : 15.0,
      "steps" : 30,
      "calories" : 1,
      "trackPoints" : [ ]
    }, {
      "activity" : "walking",
      "group" : "walking",
      "manual" : false,
      "startTime" : "20140609T233039-0400",
      "endTime" : "20140609T233139-0400",
      "duration" : 60.0,
      "distance" : 30.0,
      "steps" : 51,
      "calories" : 2,
      "trackPoints" : [ ]
    } ],
    "lastUpdate" : "20140807T114103Z"
  } ],
  "caloriesIdle" : 1875,
  "lastUpdate" : "20140807T114103Z"
} ]