[ {
  "date" : "20140816",
  "summary" : [ {
    "activity" : "walking",
    "group" : "walking",
    "duration" : 4732.0,
    "distance" : 5823.0,
    "steps" : 7550,
    "calories" : 379
  } ],
  "segments" : [ {
    "type" : "place",
    "startTime" : "20140815T143542-0500",
    "endTime" : "20140816T100655-0500",
    "activities" : [ {
      "activity" : "walking",
      "group" : "walking",
      "manual" : false,
      "startTime" : "20140816T062118-0500",
      "endTime" : "20140816T062148-0500",
      "duration" : 30.0,
      "distance" : 15.0,
      "steps" : 30,
      "calories" : 1
    }, {
      "activity" : "walking",
      "group" : "walking",
      "manual" : false,
      "startTime" : "20140816T085623-0500",
      "endTime" : "20140816T085729-0500",
      "duration" : 66.0,
      "distance" : 50.0,
      "steps" : 99,
      "calories" : 3
    }, {
      "activity" : "walking",
      "group" : "walking",
      "manual" : false,
      "startTime" : "20140816T090000-0500",
      "endTime" : "20140816T090324-0500",
      "duration" : 204.0,
      "distance" : 199.0,
      "steps" : 265,
      "calories" : 13
    } ],
    "lastUpdate" : "20140816T175738Z"
  }, {
    "type" : "move",
    "startTime" : "20140816T100655-0500",
    "endTime" : "20140816T102721-0500",
    "activities" : [ {
      "activity" : "walking",
      "group" : "walking",
      "manual" : false,
      "startTime" : "20140816T100655-0500",
      "endTime" : "20140816T102720-0500",
      "duration" : 1225.0,
      "distance" : 1368.0,
      "steps" : 2030,
      "calories" : 89
    } ],
    "lastUpdate" : "20140816T175738Z"
  }, {
    "type" : "move",
    "startTime" : "20140816T104202-0500",
    "endTime" : "20140816T105331-0500",
    "activities" : [ {
      "activity" : "walking",
      "group" : "walking",
      "manual" : false,
      "startTime" : "20140816T104202-0500",
      "endTime" : "20140816T105331-0500",
      "duration" : 689.0,
      "distance" : 1060.0,
      "steps" : 984,
      "calories" : 69
    } ],
    "lastUpdate" : "20140816T175738Z"
  }, {
    "type" : "move",
    "startTime" : "20140816T125419-0500",
    "endTime" : "20140816T130403-0500",
    "activities" : [ {
      "activity" : "walking",
      "group" : "walking",
      "manual" : false,
      "startTime" : "20140816T125419-0500",
      "endTime" : "20140816T130404-0500",
      "duration" : 585.0,
      "distance" : 779.0,
      "steps" : 1101,
      "calories" : 51
    } ],
    "lastUpdate" : "20140816T223758Z"
  }, {
    "type" : "place",
    "startTime" : "20140816T130403-0500",
    "endTime" : "20140816T133616-0500",
    "activities" : [ {
      "activity" : "walking",
      "group" : "walking",
      "manual" : false,
      "startTime" : "20140816T130526-0500",
      "endTime" : "20140816T130726-0500",
      "duration" : 120.0,
      "distance" : 144.0,
      "steps" : 193,
      "calories" : 9
    } ],
    "lastUpdate" : "20140816T223758Z"
  }, {
    "type" : "move",
    "startTime" : "20140816T133616-0500",
    "endTime" : "20140816T140246-0500",
    "activities" : [ {
      "activity" : "walking",
      "group" : "walking",
      "manual" : false,
      "startTime" : "20140816T133616-0500",
      "endTime" : "20140816T140246-0500",
      "duration" : 1590.0,
      "distance" : 2076.0,
      "steps" : 2593,
      "calories" : 135
    } ],
    "lastUpdate" : "20140816T223758Z"
  }, {
    "type" : "place",
    "startTime" : "20140816T140246-0500",
    "endTime" : "20140816T193825-0500",
    "activities" : [ {
      "activity" : "walking",
      "group" : "walking",
      "manual" : false,
      "startTime" : "20140816T141558-0500",
      "endTime" : "20140816T141728-0500",
      "duration" : 90.0,
      "distance" : 45.0,
      "steps" : 80,
      "calories" : 3
    }, {
      "activity" : "walking",
      "group" : "walking",
      "manual" : false,
      "startTime" : "20140816T183353-0500",
      "endTime" : "20140816T183453-0500",
      "duration" : 60.0,
      "distance" : 41.0,
      "steps" : 81,
      "calories" : 3
    }, {
      "activity" : "walking",
      "group" : "walking",
      "manual" : false,
      "startTime" : "20140816T191501-0500",
      "endTime" : "20140816T191531-0500",
      "duration" : 30.0,
      "distance" : 25.0,
      "steps" : 51,
      "calories" : 2
    } ],
    "lastUpdate" : "20140817T030701Z"
  }, {
    "type" : "place",
    "startTime" : "20140816T203248-0500",
    "endTime" : "20140817T070300-0500",
    "activities" : [ {
      "activity" : "walking",
      "group" : "walking",
      "manual" : false,
      "startTime" : "20140816T222951-0500",
      "endTime" : "20140816T223034-0500",
      "duration" : 43.0,
      "distance" : 21.0,
      "steps" : 43,
      "calories" : 1
    } ],
    "lastUpdate" : "20140817T132740Z"
  } ],
  "caloriesIdle" : 1875,
  "lastUpdate" : "20140817T132740Z"
} ]