[ {
  "date" : "20131221",
  "segments" : [ {
    "type" : "place",
    "startTime" : "20131220T235702-0500",
    "endTime" : "20131221T001243-0500",
    "place" : {
      "id" : 14012057,
      "type" : "unknown",
      "location" : {
        "lat" : 40.445576427,
        "lon" : -79.9905408882
      }
    },
    "lastUpdate" : "20131221T183430Z"
  }, {
    "type" : "place",
    "startTime" : "20131221T022707-0500",
    "endTime" : "20131221T024042-0500",
    "place" : {
      "id" : 14090299,
      "type" : "unknown",
      "location" : {
        "lat" : 41.293405976,
        "lon" : -81.4938037011
      }
    },
    "lastUpdate" : "20131221T183430Z"
  }, {
    "type" : "place",
    "startTime" : "20131221T031035-0500",
    "endTime" : "20131221T031835-0500",
    "place" : {
      "id" : 14090300,
      "type" : "unknown",
      "location" : {
        "lat" : 41.5031261642,
        "lon" : -81.7011237976
      }
    },
    "lastUpdate" : "20131221T183430Z"
  }, {
    "type" : "place",
    "startTime" : "20131221T072947-0500",
    "endTime" : "20131221T073646-0500",
    "place" : {
      "id" : 14090301,
      "type" : "unknown",
      "location" : {
        "lat" : 41.6790340067,
        "lon" : -85.9753982822
      }
    },
    "lastUpdate" : "20131221T183430Z"
  }, {
    "type" : "place",
    "startTime" : "20131221T102218-0500",
    "endTime" : "20131221T103657-0500",
    "place" : {
      "id" : 9123571,
      "name" : "Chicago Union Station",
      "type" : "foursquare",
      "foursquareId" : "45840daef964a520923f1fe3",
      "location" : {
        "lat" : 41.87860419025647,
        "lon" : -87.63901233673096
      }
    },
    "lastUpdate" : "20131221T183450Z"
  }, {
    "type" : "place",
    "startTime" : "20131221T114708-0500",
    "endTime" : "20131221T125042-0500",
    "place" : {
      "id" : 14171773,
      "name" : "999 S Batavia Ave",
      "type" : "home",
      "location" : {
        "lat" : 41.8771046037,
        "lon" : -88.3111773419
      }
    },
    "lastUpdate" : "20131221T201725Z"
  }, {
    "type" : "place",
    "startTime" : "20131221T125930-0500",
    "endTime" : "20131221T141337-0500",
    "place" : {
      "id" : 14171904,
      "name" : "945 S Batavia Ave",
      "type" : "foursquare",
      "foursquareId" : "4f629428e4b075c7117d49d3",
      "location" : {
        "lat" : 41.87250621617115,
        "lon" : -88.30935165928999
      }
    },
    "lastUpdate" : "20131221T201759Z"
  }, {
    "type" : "place",
    "startTime" : "20131221T142212-0500",
    "endTime" : "20131221T145817-0500",
    "place" : {
      "id" : 14162469,
      "name" : "Goody's",
      "type" : "foursquare",
      "foursquareId" : "4be05fe32aed2d7f3924c86f",
      "location" : {
        "lat" : 41.89998623,
        "lon" : -88.33660727
      }
    },
    "lastUpdate" : "20131221T203630Z"
  }, {
    "type" : "place",
    "startTime" : "20131221T150812-0500",
    "endTime" : "20131221T152833-0500",
    "place" : {
      "id" : 14172011,
      "name" : "945 S Batavia Ave",
      "type" : "foursquare",
      "foursquareId" : "4f629428e4b075c7117d49d3",
      "location" : {
        "lat" : 41.87250621617115,
        "lon" : -88.30935165928999
      }
    },
    "lastUpdate" : "20131221T222514Z"
  }, {
    "type" : "place",
    "startTime" : "20131221T153727-0500",
    "endTime" : "20131222T142815-0500",
    "place" : {
      "id" : 14486471,
      "name" : "945 S Batavia Ave",
      "type" : "foursquare",
      "foursquareId" : "4f629428e4b075c7117d49d3",
      "location" : {
        "lat" : 41.87250621617115,
        "lon" : -88.30935165928999
      }
    },
    "lastUpdate" : "20131223T020929Z"
  } ],
  "lastUpdate" : "20131223T020929Z"
} ]