[ {
  "date" : "20141019",
  "segments" : [ {
    "type" : "place",
    "startTime" : "20141018T210227-0400",
    "endTime" : "20141019T083958-0400",
    "place" : {
      "id" : 9869005,
      "name" : "Home",
      "type" : "home",
      "location" : {
        "lat" : 42.3754311174,
        "lon" : -71.1114458017
      }
    },
    "lastUpdate" : "20141019T135034Z"
  }, {
    "type" : "place",
    "startTime" : "20141019T084405-0400",
    "endTime" : "20141019T084626-0400",
    "place" : {
      "id" : 9869004,
      "name" : "Broadway Marketplace",
      "type" : "foursquare",
      "foursquareId" : "4a661612f964a520ffc71fe3",
      "foursquareCategoryIds" : [ "4bf58dd8d48988d118951735", "4bf58dd8d48988d1f5941735" ],
      "location" : {
        "lat" : 42.37405171427381,
        "lon" : -71.11300484548056
      }
    },
    "lastUpdate" : "20141019T135034Z"
  }, {
    "type" : "place",
    "startTime" : "20141019T085047-0400",
    "endTime" : "20141019T134917-0400",
    "place" : {
      "id" : 9869005,
      "name" : "Home",
      "type" : "home",
      "location" : {
        "lat" : 42.3754311174,
        "lon" : -71.1114458017
      }
    },
    "lastUpdate" : "20141019T200035Z"
  }, {
    "type" : "place",
    "startTime" : "20141019T141412-0400",
    "endTime" : "20141019T154611-0400",
    "place" : {
      "id" : 87938770,
      "name" : "Harvard Innovation Lab",
      "type" : "foursquare",
      "foursquareId" : "4e5d4676ae60839ea2e29e64",
      "foursquareCategoryIds" : [ "4bf58dd8d48988d19f941735" ],
      "location" : {
        "lat" : 42.36427488545988,
        "lon" : -71.12402979165076
      }
    },
    "lastUpdate" : "20141019T213400Z"
  }, {
    "type" : "place",
    "startTime" : "20141019T162751-0400",
    "endTime" : "20141019T170329-0400",
    "place" : {
      "id" : 30131139,
      "name" : "Tory Row",
      "type" : "foursquare",
      "foursquareId" : "49e79621f964a520cf641fe3",
      "foursquareCategoryIds" : [ "4bf58dd8d48988d14e941735" ],
      "location" : {
        "lat" : 42.373379,
        "lon" : -71.119457
      }
    },
    "lastUpdate" : "20141019T213400Z"
  }, {
    "type" : "place",
    "startTime" : "20141019T171337-0400",
    "endTime" : "20141019T181009-0400",
    "place" : {
      "id" : 9869005,
      "name" : "Home",
      "type" : "home",
      "location" : {
        "lat" : 42.3754311174,
        "lon" : -71.1114458017
      }
    },
    "lastUpdate" : "20141019T230851Z"
  }, {
    "type" : "place",
    "startTime" : "20141019T183002-0400",
    "endTime" : "20141019T184526-0400",
    "place" : {
      "id" : 89281744,
      "type" : "unknown",
      "location" : {
        "lat" : 42.3711849193,
        "lon" : -71.1146043361
      }
    },
    "lastUpdate" : "20141020T021221Z"
  }, {
    "type" : "place",
    "startTime" : "20141019T191205-0400",
    "endTime" : "20141020T072735-0400",
    "place" : {
      "id" : 9869005,
      "name" : "Home",
      "type" : "home",
      "location" : {
        "lat" : 42.3754311174,
        "lon" : -71.1114458017
      }
    },
    "lastUpdate" : "20141020T143958Z"
  } ],
  "lastUpdate" : "20141020T143958Z"
} ]